m4rtin/__init__.py
m4rtin/courses.py
m4rtin/utils.py
m4rtin-0.3.0.dist-info/METADATA
m4rtin-0.3.0.dist-info/WHEEL
m4rtin-0.3.0.dist-info/top_level.txt
m4rtin-0.3.0.dist-info/RECORD
