Metadata-Version: 2.2
Name: m4rtin
Version: 0.3.0
Summary: Una biblioteca para consultar cursos de Hack4u
Home-page: https://hack4u.io
Author: Martín Martín
Dynamic: author
Dynamic: description
Dynamic: description-content-type
Dynamic: home-page
Dynamic: summary
